[
  {
    "cipCode": "2601",
    "programName": "Biology, General.",
    "credentialLevel": "Master's Degree",
    "credentialCode": "5",
    "graduates": {
      "total": 14,
      "workingCount": 0
    },
    "earnings": {
      "annual": 0,
      "monthly": 0,
      "byDemographic": {
        "male": 0,
        "nonMale": 0,
        "pellRecipient": 0,
        "nonPellRecipient": 0
      }
    },
    "deliveryMethod": 1
  },
  {
    "cipCode": "2601",
    "programName": "Biology, General.",
    "credentialLevel": "Doctoral Degree",
    "credentialCode": "6",
    "graduates": {
      "total": 41,
      "workingCount": 18
    },
    "earnings": {
      "annual": 159788,
      "monthly": 13316,
      "byDemographic": {
        "male": 0,
        "nonMale": 0,
        "pellRecipient": 0,
        "nonPellRecipient": 0
      }
    },
    "deliveryMethod": 1
  },
  {
    "cipCode": "5112",
    "programName": "Medicine.",
    "credentialLevel": "Doctoral Degree",
    "credentialCode": "6",
    "graduates": {
      "total": 0,
      "workingCount": 103
    },
    "earnings": {
      "annual": 128373,
      "monthly": 10698,
      "byDemographic": {
        "male": 109246,
        "nonMale": 129116,
        "pellRecipient": 127411,
        "nonPellRecipient": 120444
      }
    },
    "deliveryMethod": 0
  },
  {
    "cipCode": "5112",
    "programName": "Medicine.",
    "credentialLevel": "First Professional Degree",
    "credentialCode": "7",
    "graduates": {
      "total": 169,
      "workingCount": 0
    },
    "earnings": {
      "annual": 0,
      "monthly": 0,
      "byDemographic": {
        "male": 0,
        "nonMale": 0,
        "pellRecipient": 0,
        "nonPellRecipient": 0
      }
    },
    "deliveryMethod": 1
  },
  {
    "cipCode": "5138",
    "programName": "Registered Nursing, Nursing Administration, Nursing Research and Clinical Nursing.",
    "credentialLevel": "Master's Degree",
    "credentialCode": "5",
    "graduates": {
      "total": 45,
      "workingCount": 44
    },
    "earnings": {
      "annual": 116142,
      "monthly": 9679,
      "byDemographic": {
        "male": 0,
        "nonMale": 0,
        "pellRecipient": 0,
        "nonPellRecipient": 0
      }
    },
    "deliveryMethod": 1
  },
  {
    "cipCode": "5138",
    "programName": "Registered Nursing, Nursing Administration, Nursing Research and Clinical Nursing.",
    "credentialLevel": "Doctoral Degree",
    "credentialCode": "6",
    "graduates": {
      "total": 4,
      "workingCount": 0
    },
    "earnings": {
      "annual": 0,
      "monthly": 0,
      "byDemographic": {
        "male": 0,
        "nonMale": 0,
        "pellRecipient": 0,
        "nonPellRecipient": 0
      }
    },
    "deliveryMethod": 1
  },
  {
    "cipCode": "5138",
    "programName": "Registered Nursing, Nursing Administration, Nursing Research and Clinical Nursing.",
    "credentialLevel": "First Professional Degree",
    "credentialCode": "7",
    "graduates": {
      "total": 47,
      "workingCount": 0
    },
    "earnings": {
      "annual": 0,
      "monthly": 0,
      "byDemographic": {
        "male": 0,
        "nonMale": 0,
        "pellRecipient": 0,
        "nonPellRecipient": 0
      }
    },
    "deliveryMethod": 1
  },
  {
    "cipCode": "5138",
    "programName": "Registered Nursing, Nursing Administration, Nursing Research and Clinical Nursing.",
    "credentialLevel": "Graduate/Professional Certificate",
    "credentialCode": "8",
    "graduates": {
      "total": 6,
      "workingCount": 0
    },
    "earnings": {
      "annual": 0,
      "monthly": 0,
      "byDemographic": {
        "male": 0,
        "nonMale": 0,
        "pellRecipient": 0,
        "nonPellRecipient": 0
      }
    },
    "deliveryMethod": 1
  }
]