[
  {
    "cipCode": "0409",
    "programName": "Architectural Sciences and Technology.",
    "credentialLevel": "Associate's Degree",
    "credentialCode": "2",
    "graduates": {
      "total": 4,
      "workingCount": 0
    },
    "earnings": {
      "annual": 0,
      "monthly": 0,
      "byDemographic": {
        "male": 0,
        "nonMale": 0,
        "pellRecipient": 0,
        "nonPellRecipient": 0
      }
    },
    "deliveryMethod": 1
  },
  {
    "cipCode": "0901",
    "programName": "Communication and Media Studies.",
    "credentialLevel": "Associate's Degree",
    "credentialCode": "2",
    "graduates": {
      "total": 9,
      "workingCount": 0
    },
    "earnings": {
      "annual": 0,
      "monthly": 0,
      "byDemographic": {
        "male": 0,
        "nonMale": 0,
        "pellRecipient": 0,
        "nonPellRecipient": 0
      }
    },
    "deliveryMethod": 3
  },
  {
    "cipCode": "1101",
    "programName": "Computer and Information Sciences, General.",
    "credentialLevel": "Undergraduate Certificate or Diploma",
    "credentialCode": "1",
    "graduates": {
      "total": 10,
      "workingCount": 0
    },
    "earnings": {
      "annual": 0,
      "monthly": 0,
      "byDemographic": {
        "male": 0,
        "nonMale": 0,
        "pellRecipient": 0,
        "nonPellRecipient": 0
      }
    },
    "deliveryMethod": 3
  },
  {
    "cipCode": "1101",
    "programName": "Computer and Information Sciences, General.",
    "credentialLevel": "Associate's Degree",
    "credentialCode": "2",
    "graduates": {
      "total": 35,
      "workingCount": 0
    },
    "earnings": {
      "annual": 0,
      "monthly": 0,
      "byDemographic": {
        "male": 0,
        "nonMale": 0,
        "pellRecipient": 0,
        "nonPellRecipient": 0
      }
    },
    "deliveryMethod": 3
  },
  {
    "cipCode": "1107",
    "programName": "Computer Science.",
    "credentialLevel": "Associate's Degree",
    "credentialCode": "2",
    "graduates": {
      "total": 18,
      "workingCount": 0
    },
    "earnings": {
      "annual": 0,
      "monthly": 0,
      "byDemographic": {
        "male": 0,
        "nonMale": 0,
        "pellRecipient": 0,
        "nonPellRecipient": 0
      }
    },
    "deliveryMethod": 1
  },
  {
    "cipCode": "1203",
    "programName": "Funeral Service and Mortuary Science.",
    "credentialLevel": "Associate's Degree",
    "credentialCode": "2",
    "graduates": {
      "total": 28,
      "workingCount": 25
    },
    "earnings": {
      "annual": 55507,
      "monthly": 4626,
      "byDemographic": {
        "male": 0,
        "nonMale": 0,
        "pellRecipient": 0,
        "nonPellRecipient": 0
      }
    },
    "deliveryMethod": 1
  },
  {
    "cipCode": "1312",
    "programName": "Teacher Education and Professional Development, Specific Levels and Methods.",
    "credentialLevel": "Associate's Degree",
    "credentialCode": "2",
    "graduates": {
      "total": 21,
      "workingCount": 0
    },
    "earnings": {
      "annual": 0,
      "monthly": 0,
      "byDemographic": {
        "male": 0,
        "nonMale": 0,
        "pellRecipient": 0,
        "nonPellRecipient": 0
      }
    },
    "deliveryMethod": 3
  },
  {
    "cipCode": "1401",
    "programName": "Engineering, General.",
    "credentialLevel": "Associate's Degree",
    "credentialCode": "2",
    "graduates": {
      "total": 22,
      "workingCount": 0
    },
    "earnings": {
      "annual": 0,
      "monthly": 0,
      "byDemographic": {
        "male": 0,
        "nonMale": 0,
        "pellRecipient": 0,
        "nonPellRecipient": 0
      }
    },
    "deliveryMethod": 1
  },
  {
    "cipCode": "1438",
    "programName": "Surveying Engineering.",
    "credentialLevel": "Undergraduate Certificate or Diploma",
    "credentialCode": "1",
    "graduates": {
      "total": 2,
      "workingCount": 0
    },
    "earnings": {
      "annual": 0,
      "monthly": 0,
      "byDemographic": {
        "male": 0,
        "nonMale": 0,
        "pellRecipient": 0,
        "nonPellRecipient": 0
      }
    },
    "deliveryMethod": 1
  },
  {
    "cipCode": "1502",
    "programName": "Civil Engineering Technologies/Technicians.",
    "credentialLevel": "Undergraduate Certificate or Diploma",
    "credentialCode": "1",
    "graduates": {
      "total": 1,
      "workingCount": 0
    },
    "earnings": {
      "annual": 0,
      "monthly": 0,
      "byDemographic": {
        "male": 0,
        "nonMale": 0,
        "pellRecipient": 0,
        "nonPellRecipient": 0
      }
    },
    "deliveryMethod": 1
  },
  {
    "cipCode": "1503",
    "programName": "Electrical Engineering Technologies/Technicians.",
    "credentialLevel": "Undergraduate Certificate or Diploma",
    "credentialCode": "1",
    "graduates": {
      "total": 70,
      "workingCount": 0
    },
    "earnings": {
      "annual": 0,
      "monthly": 0,
      "byDemographic": {
        "male": 0,
        "nonMale": 0,
        "pellRecipient": 0,
        "nonPellRecipient": 0
      }
    },
    "deliveryMethod": 2
  },
  {
    "cipCode": "1506",
    "programName": "Industrial Production Technologies/Technicians.",
    "credentialLevel": "Undergraduate Certificate or Diploma",
    "credentialCode": "1",
    "graduates": {
      "total": 23,
      "workingCount": 0
    },
    "earnings": {
      "annual": 0,
      "monthly": 0,
      "byDemographic": {
        "male": 0,
        "nonMale": 0,
        "pellRecipient": 0,
        "nonPellRecipient": 0
      }
    },
    "deliveryMethod": 1
  },
  {
    "cipCode": "1506",
    "programName": "Industrial Production Technologies/Technicians.",
    "credentialLevel": "Associate's Degree",
    "credentialCode": "2",
    "graduates": {
      "total": 13,
      "workingCount": 0
    },
    "earnings": {
      "annual": 0,
      "monthly": 0,
      "byDemographic": {
        "male": 0,
        "nonMale": 0,
        "pellRecipient": 0,
        "nonPellRecipient": 0
      }
    },
    "deliveryMethod": 1
  },
  {
    "cipCode": "1508",
    "programName": "Mechanical Engineering Related Technologies/Technicians.",
    "credentialLevel": "Associate's Degree",
    "credentialCode": "2",
    "graduates": {
      "total": 17,
      "workingCount": 0
    },
    "earnings": {
      "annual": 0,
      "monthly": 0,
      "byDemographic": {
        "male": 0,
        "nonMale": 0,
        "pellRecipient": 0,
        "nonPellRecipient": 0
      }
    },
    "deliveryMethod": 1
  },
  {
    "cipCode": "1513",
    "programName": "Drafting/Design Engineering Technologies/Technicians.",
    "credentialLevel": "Undergraduate Certificate or Diploma",
    "credentialCode": "1",
    "graduates": {
      "total": 4,
      "workingCount": 0
    },
    "earnings": {
      "annual": 0,
      "monthly": 0,
      "byDemographic": {
        "male": 0,
        "nonMale": 0,
        "pellRecipient": 0,
        "nonPellRecipient": 0
      }
    },
    "deliveryMethod": 1
  },
  {
    "cipCode": "1907",
    "programName": "Human Development, Family Studies, and Related Services.",
    "credentialLevel": "Undergraduate Certificate or Diploma",
    "credentialCode": "1",
    "graduates": {
      "total": 39,
      "workingCount": 0
    },
    "earnings": {
      "annual": 0,
      "monthly": 0,
      "byDemographic": {
        "male": 0,
        "nonMale": 0,
        "pellRecipient": 0,
        "nonPellRecipient": 0
      }
    },
    "deliveryMethod": 1
  },
  {
    "cipCode": "1907",
    "programName": "Human Development, Family Studies, and Related Services.",
    "credentialLevel": "Associate's Degree",
    "credentialCode": "2",
    "graduates": {
      "total": 13,
      "workingCount": 0
    },
    "earnings": {
      "annual": 0,
      "monthly": 0,
      "byDemographic": {
        "male": 0,
        "nonMale": 0,
        "pellRecipient": 0,
        "nonPellRecipient": 0
      }
    },
    "deliveryMethod": 1
  },
  {
    "cipCode": "2203",
    "programName": "Legal Support Services.",
    "credentialLevel": "Undergraduate Certificate or Diploma",
    "credentialCode": "1",
    "graduates": {
      "total": 15,
      "workingCount": 0
    },
    "earnings": {
      "annual": 0,
      "monthly": 0,
      "byDemographic": {
        "male": 0,
        "nonMale": 0,
        "pellRecipient": 0,
        "nonPellRecipient": 0
      }
    },
    "deliveryMethod": 1
  },
  {
    "cipCode": "2401",
    "programName": "Liberal Arts and Sciences, General Studies and Humanities.",
    "credentialLevel": "Undergraduate Certificate or Diploma",
    "credentialCode": "1",
    "graduates": {
      "total": 262,
      "workingCount": 33
    },
    "earnings": {
      "annual": 43480,
      "monthly": 3623,
      "byDemographic": {
        "male": 0,
        "nonMale": 0,
        "pellRecipient": 0,
        "nonPellRecipient": 0
      }
    },
    "deliveryMethod": 3
  },
  {
    "cipCode": "2401",
    "programName": "Liberal Arts and Sciences, General Studies and Humanities.",
    "credentialLevel": "Associate's Degree",
    "credentialCode": "2",
    "graduates": {
      "total": 320,
      "workingCount": 245
    },
    "earnings": {
      "annual": 43192,
      "monthly": 3599,
      "byDemographic": {
        "male": 43046,
        "nonMale": 43226,
        "pellRecipient": 42670,
        "nonPellRecipient": 46074
      }
    },
    "deliveryMethod": 1
  },
  {
    "cipCode": "3001",
    "programName": "Biological and Physical Sciences.",
    "credentialLevel": "Associate's Degree",
    "credentialCode": "2",
    "graduates": {
      "total": 29,
      "workingCount": 0
    },
    "earnings": {
      "annual": 0,
      "monthly": 0,
      "byDemographic": {
        "male": 0,
        "nonMale": 0,
        "pellRecipient": 0,
        "nonPellRecipient": 0
      }
    },
    "deliveryMethod": 1
  },
  {
    "cipCode": "3014",
    "programName": "Museology/Museum Studies.",
    "credentialLevel": "Undergraduate Certificate or Diploma",
    "credentialCode": "1",
    "graduates": {
      "total": 5,
      "workingCount": 0
    },
    "earnings": {
      "annual": 0,
      "monthly": 0,
      "byDemographic": {
        "male": 0,
        "nonMale": 0,
        "pellRecipient": 0,
        "nonPellRecipient": 0
      }
    },
    "deliveryMethod": 3
  },
  {
    "cipCode": "4201",
    "programName": "Psychology, General.",
    "credentialLevel": "Associate's Degree",
    "credentialCode": "2",
    "graduates": {
      "total": 21,
      "workingCount": 0
    },
    "earnings": {
      "annual": 0,
      "monthly": 0,
      "byDemographic": {
        "male": 0,
        "nonMale": 0,
        "pellRecipient": 0,
        "nonPellRecipient": 0
      }
    },
    "deliveryMethod": 3
  },
  {
    "cipCode": "4301",
    "programName": "Criminal Justice and Corrections.",
    "credentialLevel": "Undergraduate Certificate or Diploma",
    "credentialCode": "1",
    "graduates": {
      "total": 33,
      "workingCount": 0
    },
    "earnings": {
      "annual": 0,
      "monthly": 0,
      "byDemographic": {
        "male": 0,
        "nonMale": 0,
        "pellRecipient": 0,
        "nonPellRecipient": 0
      }
    },
    "deliveryMethod": 3
  },
  {
    "cipCode": "4301",
    "programName": "Criminal Justice and Corrections.",
    "credentialLevel": "Associate's Degree",
    "credentialCode": "2",
    "graduates": {
      "total": 28,
      "workingCount": 0
    },
    "earnings": {
      "annual": 0,
      "monthly": 0,
      "byDemographic": {
        "male": 0,
        "nonMale": 0,
        "pellRecipient": 0,
        "nonPellRecipient": 0
      }
    },
    "deliveryMethod": 3
  },
  {
    "cipCode": "4600",
    "programName": "Construction Trades, General.",
    "credentialLevel": "Undergraduate Certificate or Diploma",
    "credentialCode": "1",
    "graduates": {
      "total": 6,
      "workingCount": 0
    },
    "earnings": {
      "annual": 0,
      "monthly": 0,
      "byDemographic": {
        "male": 0,
        "nonMale": 0,
        "pellRecipient": 0,
        "nonPellRecipient": 0
      }
    },
    "deliveryMethod": 1
  },
  {
    "cipCode": "4603",
    "programName": "Electrical and Power Transmission Installers.",
    "credentialLevel": "Associate's Degree",
    "credentialCode": "2",
    "graduates": {
      "total": 8,
      "workingCount": 0
    },
    "earnings": {
      "annual": 0,
      "monthly": 0,
      "byDemographic": {
        "male": 0,
        "nonMale": 0,
        "pellRecipient": 0,
        "nonPellRecipient": 0
      }
    },
    "deliveryMethod": 1
  },
  {
    "cipCode": "4701",
    "programName": "Electrical/Electronics Maintenance and Repair Technology.",
    "credentialLevel": "Undergraduate Certificate or Diploma",
    "credentialCode": "1",
    "graduates": {
      "total": 2,
      "workingCount": 0
    },
    "earnings": {
      "annual": 0,
      "monthly": 0,
      "byDemographic": {
        "male": 0,
        "nonMale": 0,
        "pellRecipient": 0,
        "nonPellRecipient": 0
      }
    },
    "deliveryMethod": 1
  },
  {
    "cipCode": "4702",
    "programName": "Heating, Air Conditioning, Ventilation and Refrigeration Maintenance Technology/Technician (HAC, HACR, HVAC, HVACR).",
    "credentialLevel": "Undergraduate Certificate or Diploma",
    "credentialCode": "1",
    "graduates": {
      "total": 16,
      "workingCount": 0
    },
    "earnings": {
      "annual": 0,
      "monthly": 0,
      "byDemographic": {
        "male": 0,
        "nonMale": 0,
        "pellRecipient": 0,
        "nonPellRecipient": 0
      }
    },
    "deliveryMethod": 1
  },
  {
    "cipCode": "4805",
    "programName": "Precision Metal Working.",
    "credentialLevel": "Undergraduate Certificate or Diploma",
    "credentialCode": "1",
    "graduates": {
      "total": 37,
      "workingCount": 0
    },
    "earnings": {
      "annual": 0,
      "monthly": 0,
      "byDemographic": {
        "male": 0,
        "nonMale": 0,
        "pellRecipient": 0,
        "nonPellRecipient": 0
      }
    },
    "deliveryMethod": 1
  },
  {
    "cipCode": "5005",
    "programName": "Drama/Theatre Arts and Stagecraft.",
    "credentialLevel": "Associate's Degree",
    "credentialCode": "2",
    "graduates": {
      "total": 3,
      "workingCount": 0
    },
    "earnings": {
      "annual": 0,
      "monthly": 0,
      "byDemographic": {
        "male": 0,
        "nonMale": 0,
        "pellRecipient": 0,
        "nonPellRecipient": 0
      }
    },
    "deliveryMethod": 1
  },
  {
    "cipCode": "5006",
    "programName": "Film/Video and Photographic Arts.",
    "credentialLevel": "Undergraduate Certificate or Diploma",
    "credentialCode": "1",
    "graduates": {
      "total": 7,
      "workingCount": 0
    },
    "earnings": {
      "annual": 0,
      "monthly": 0,
      "byDemographic": {
        "male": 0,
        "nonMale": 0,
        "pellRecipient": 0,
        "nonPellRecipient": 0
      }
    },
    "deliveryMethod": 1
  },
  {
    "cipCode": "5009",
    "programName": "Music.",
    "credentialLevel": "Associate's Degree",
    "credentialCode": "2",
    "graduates": {
      "total": 5,
      "workingCount": 0
    },
    "earnings": {
      "annual": 0,
      "monthly": 0,
      "byDemographic": {
        "male": 0,
        "nonMale": 0,
        "pellRecipient": 0,
        "nonPellRecipient": 0
      }
    },
    "deliveryMethod": 1
  },
  {
    "cipCode": "5099",
    "programName": "Visual and Performing Arts, Other.",
    "credentialLevel": "Undergraduate Certificate or Diploma",
    "credentialCode": "1",
    "graduates": {
      "total": 32,
      "workingCount": 0
    },
    "earnings": {
      "annual": 0,
      "monthly": 0,
      "byDemographic": {
        "male": 0,
        "nonMale": 0,
        "pellRecipient": 0,
        "nonPellRecipient": 0
      }
    },
    "deliveryMethod": 1
  },
  {
    "cipCode": "5099",
    "programName": "Visual and Performing Arts, Other.",
    "credentialLevel": "Associate's Degree",
    "credentialCode": "2",
    "graduates": {
      "total": 42,
      "workingCount": 0
    },
    "earnings": {
      "annual": 0,
      "monthly": 0,
      "byDemographic": {
        "male": 0,
        "nonMale": 0,
        "pellRecipient": 0,
        "nonPellRecipient": 0
      }
    },
    "deliveryMethod": 1
  },
  {
    "cipCode": "5100",
    "programName": "Health Services/Allied Health/Health Sciences, General.",
    "credentialLevel": "Associate's Degree",
    "credentialCode": "2",
    "graduates": {
      "total": 89,
      "workingCount": 0
    },
    "earnings": {
      "annual": 0,
      "monthly": 0,
      "byDemographic": {
        "male": 0,
        "nonMale": 0,
        "pellRecipient": 0,
        "nonPellRecipient": 0
      }
    },
    "deliveryMethod": 3
  },
  {
    "cipCode": "5109",
    "programName": "Allied Health Diagnostic, Intervention, and Treatment Professions.",
    "credentialLevel": "Undergraduate Certificate or Diploma",
    "credentialCode": "1",
    "graduates": {
      "total": 2,
      "workingCount": 0
    },
    "earnings": {
      "annual": 0,
      "monthly": 0,
      "byDemographic": {
        "male": 0,
        "nonMale": 0,
        "pellRecipient": 0,
        "nonPellRecipient": 0
      }
    },
    "deliveryMethod": 1
  },
  {
    "cipCode": "5109",
    "programName": "Allied Health Diagnostic, Intervention, and Treatment Professions.",
    "credentialLevel": "Associate's Degree",
    "credentialCode": "2",
    "graduates": {
      "total": 10,
      "workingCount": 0
    },
    "earnings": {
      "annual": 0,
      "monthly": 0,
      "byDemographic": {
        "male": 0,
        "nonMale": 0,
        "pellRecipient": 0,
        "nonPellRecipient": 0
      }
    },
    "deliveryMethod": 1
  },
  {
    "cipCode": "5115",
    "programName": "Mental and Social Health Services and Allied Professions.",
    "credentialLevel": "Undergraduate Certificate or Diploma",
    "credentialCode": "1",
    "graduates": {
      "total": 8,
      "workingCount": 35
    },
    "earnings": {
      "annual": 41863,
      "monthly": 3489,
      "byDemographic": {
        "male": 0,
        "nonMale": 0,
        "pellRecipient": 0,
        "nonPellRecipient": 0
      }
    },
    "deliveryMethod": 1
  },
  {
    "cipCode": "5115",
    "programName": "Mental and Social Health Services and Allied Professions.",
    "credentialLevel": "Associate's Degree",
    "credentialCode": "2",
    "graduates": {
      "total": 32,
      "workingCount": 41
    },
    "earnings": {
      "annual": 42050,
      "monthly": 3504,
      "byDemographic": {
        "male": 0,
        "nonMale": 0,
        "pellRecipient": 0,
        "nonPellRecipient": 0
      }
    },
    "deliveryMethod": 1
  },
  {
    "cipCode": "5135",
    "programName": "Somatic Bodywork and Related Therapeutic Services.",
    "credentialLevel": "Undergraduate Certificate or Diploma",
    "credentialCode": "1",
    "graduates": {
      "total": 10,
      "workingCount": 0
    },
    "earnings": {
      "annual": 0,
      "monthly": 0,
      "byDemographic": {
        "male": 0,
        "nonMale": 0,
        "pellRecipient": 0,
        "nonPellRecipient": 0
      }
    },
    "deliveryMethod": 1
  },
  {
    "cipCode": "5138",
    "programName": "Registered Nursing, Nursing Administration, Nursing Research and Clinical Nursing.",
    "credentialLevel": "Undergraduate Certificate or Diploma",
    "credentialCode": "1",
    "graduates": {
      "total": 10,
      "workingCount": 27
    },
    "earnings": {
      "annual": 42509,
      "monthly": 3542,
      "byDemographic": {
        "male": 0,
        "nonMale": 0,
        "pellRecipient": 0,
        "nonPellRecipient": 0
      }
    },
    "deliveryMethod": 1
  },
  {
    "cipCode": "5138",
    "programName": "Registered Nursing, Nursing Administration, Nursing Research and Clinical Nursing.",
    "credentialLevel": "Associate's Degree",
    "credentialCode": "2",
    "graduates": {
      "total": 111,
      "workingCount": 97
    },
    "earnings": {
      "annual": 75019,
      "monthly": 6252,
      "byDemographic": {
        "male": 0,
        "nonMale": 0,
        "pellRecipient": 75064,
        "nonPellRecipient": 73949
      }
    },
    "deliveryMethod": 1
  },
  {
    "cipCode": "5202",
    "programName": "Business Administration, Management and Operations.",
    "credentialLevel": "Undergraduate Certificate or Diploma",
    "credentialCode": "1",
    "graduates": {
      "total": 19,
      "workingCount": 0
    },
    "earnings": {
      "annual": 0,
      "monthly": 0,
      "byDemographic": {
        "male": 0,
        "nonMale": 0,
        "pellRecipient": 0,
        "nonPellRecipient": 0
      }
    },
    "deliveryMethod": 3
  },
  {
    "cipCode": "5202",
    "programName": "Business Administration, Management and Operations.",
    "credentialLevel": "Associate's Degree",
    "credentialCode": "2",
    "graduates": {
      "total": 107,
      "workingCount": 88
    },
    "earnings": {
      "annual": 48299,
      "monthly": 4025,
      "byDemographic": {
        "male": 50389,
        "nonMale": 45203,
        "pellRecipient": 48290,
        "nonPellRecipient": 48353
      }
    },
    "deliveryMethod": 3
  },
  {
    "cipCode": "5203",
    "programName": "Accounting and Related Services.",
    "credentialLevel": "Undergraduate Certificate or Diploma",
    "credentialCode": "1",
    "graduates": {
      "total": 6,
      "workingCount": 0
    },
    "earnings": {
      "annual": 0,
      "monthly": 0,
      "byDemographic": {
        "male": 0,
        "nonMale": 0,
        "pellRecipient": 0,
        "nonPellRecipient": 0
      }
    },
    "deliveryMethod": 3
  },
  {
    "cipCode": "5203",
    "programName": "Accounting and Related Services.",
    "credentialLevel": "Associate's Degree",
    "credentialCode": "2",
    "graduates": {
      "total": 3,
      "workingCount": 0
    },
    "earnings": {
      "annual": 0,
      "monthly": 0,
      "byDemographic": {
        "male": 0,
        "nonMale": 0,
        "pellRecipient": 0,
        "nonPellRecipient": 0
      }
    },
    "deliveryMethod": 3
  }
]