[
  {
    "cipCode": "0301",
    "programName": "Natural Resources Conservation and Research.",
    "credentialLevel": "Undergraduate Certificate or Diploma",
    "credentialCode": "1",
    "graduates": {
      "total": 16,
      "workingCount": 18
    },
    "earnings": {
      "annual": 80703,
      "monthly": 6725,
      "byDemographic": {
        "male": 0,
        "nonMale": 0,
        "pellRecipient": 0,
        "nonPellRecipient": 0
      }
    },
    "deliveryMethod": 3
  },
  {
    "cipCode": "0301",
    "programName": "Natural Resources Conservation and Research.",
    "credentialLevel": "Bachelor's Degree",
    "credentialCode": "3",
    "graduates": {
      "total": 84,
      "workingCount": 82
    },
    "earnings": {
      "annual": 74518,
      "monthly": 6210,
      "byDemographic": {
        "male": 78026,
        "nonMale": 39932,
        "pellRecipient": 67543,
        "nonPellRecipient": 75477
      }
    },
    "deliveryMethod": 3
  },
  {
    "cipCode": "0301",
    "programName": "Natural Resources Conservation and Research.",
    "credentialLevel": "Graduate/Professional Certificate",
    "credentialCode": "8",
    "graduates": {
      "total": 6,
      "workingCount": 0
    },
    "earnings": {
      "annual": 0,
      "monthly": 0,
      "byDemographic": {
        "male": 0,
        "nonMale": 0,
        "pellRecipient": 0,
        "nonPellRecipient": 0
      }
    },
    "deliveryMethod": 3
  },
  {
    "cipCode": "1101",
    "programName": "Computer and Information Sciences, General.",
    "credentialLevel": "Undergraduate Certificate or Diploma",
    "credentialCode": "1",
    "graduates": {
      "total": 7,
      "workingCount": 0
    },
    "earnings": {
      "annual": 0,
      "monthly": 0,
      "byDemographic": {
        "male": 0,
        "nonMale": 0,
        "pellRecipient": 0,
        "nonPellRecipient": 0
      }
    },
    "deliveryMethod": 3
  },
  {
    "cipCode": "1101",
    "programName": "Computer and Information Sciences, General.",
    "credentialLevel": "Bachelor's Degree",
    "credentialCode": "3",
    "graduates": {
      "total": 107,
      "workingCount": 83
    },
    "earnings": {
      "annual": 82769,
      "monthly": 6897,
      "byDemographic": {
        "male": 93491,
        "nonMale": 73089,
        "pellRecipient": 81878,
        "nonPellRecipient": 82451
      }
    },
    "deliveryMethod": 3
  },
  {
    "cipCode": "1110",
    "programName": "Computer/Information Technology Administration and Management.",
    "credentialLevel": "Undergraduate Certificate or Diploma",
    "credentialCode": "1",
    "graduates": {
      "total": 2,
      "workingCount": 0
    },
    "earnings": {
      "annual": 0,
      "monthly": 0,
      "byDemographic": {
        "male": 0,
        "nonMale": 0,
        "pellRecipient": 0,
        "nonPellRecipient": 0
      }
    },
    "deliveryMethod": 3
  },
  {
    "cipCode": "1110",
    "programName": "Computer/Information Technology Administration and Management.",
    "credentialLevel": "Bachelor's Degree",
    "credentialCode": "3",
    "graduates": {
      "total": 63,
      "workingCount": 0
    },
    "earnings": {
      "annual": 0,
      "monthly": 0,
      "byDemographic": {
        "male": 0,
        "nonMale": 0,
        "pellRecipient": 0,
        "nonPellRecipient": 0
      }
    },
    "deliveryMethod": 3
  },
  {
    "cipCode": "1507",
    "programName": "Quality Control and Safety Technologies/Technicians.",
    "credentialLevel": "Undergraduate Certificate or Diploma",
    "credentialCode": "1",
    "graduates": {
      "total": 43,
      "workingCount": 41
    },
    "earnings": {
      "annual": 85911,
      "monthly": 7159,
      "byDemographic": {
        "male": 0,
        "nonMale": 0,
        "pellRecipient": 74181,
        "nonPellRecipient": 110565
      }
    },
    "deliveryMethod": 3
  },
  {
    "cipCode": "1507",
    "programName": "Quality Control and Safety Technologies/Technicians.",
    "credentialLevel": "Associate's Degree",
    "credentialCode": "2",
    "graduates": {
      "total": 364,
      "workingCount": 348
    },
    "earnings": {
      "annual": 84183,
      "monthly": 7015,
      "byDemographic": {
        "male": 91042,
        "nonMale": 66938,
        "pellRecipient": 82460,
        "nonPellRecipient": 90051
      }
    },
    "deliveryMethod": 3
  },
  {
    "cipCode": "1507",
    "programName": "Quality Control and Safety Technologies/Technicians.",
    "credentialLevel": "Bachelor's Degree",
    "credentialCode": "3",
    "graduates": {
      "total": 683,
      "workingCount": 508
    },
    "earnings": {
      "annual": 91754,
      "monthly": 7646,
      "byDemographic": {
        "male": 97749,
        "nonMale": 76617,
        "pellRecipient": 87503,
        "nonPellRecipient": 106271
      }
    },
    "deliveryMethod": 3
  },
  {
    "cipCode": "1507",
    "programName": "Quality Control and Safety Technologies/Technicians.",
    "credentialLevel": "Post-baccalaureate Certificate",
    "credentialCode": "4",
    "graduates": {
      "total": 0,
      "workingCount": 17
    },
    "earnings": {
      "annual": 77603,
      "monthly": 6467,
      "byDemographic": {
        "male": 0,
        "nonMale": 0,
        "pellRecipient": 0,
        "nonPellRecipient": 0
      }
    },
    "deliveryMethod": 0
  },
  {
    "cipCode": "1507",
    "programName": "Quality Control and Safety Technologies/Technicians.",
    "credentialLevel": "Master's Degree",
    "credentialCode": "5",
    "graduates": {
      "total": 384,
      "workingCount": 226
    },
    "earnings": {
      "annual": 94061,
      "monthly": 7838,
      "byDemographic": {
        "male": 102680,
        "nonMale": 77119,
        "pellRecipient": 91864,
        "nonPellRecipient": 97287
      }
    },
    "deliveryMethod": 3
  },
  {
    "cipCode": "1507",
    "programName": "Quality Control and Safety Technologies/Technicians.",
    "credentialLevel": "Graduate/Professional Certificate",
    "credentialCode": "8",
    "graduates": {
      "total": 18,
      "workingCount": 0
    },
    "earnings": {
      "annual": 0,
      "monthly": 0,
      "byDemographic": {
        "male": 0,
        "nonMale": 0,
        "pellRecipient": 0,
        "nonPellRecipient": 0
      }
    },
    "deliveryMethod": 3
  },
  {
    "cipCode": "2401",
    "programName": "Liberal Arts and Sciences, General Studies and Humanities.",
    "credentialLevel": "Associate's Degree",
    "credentialCode": "2",
    "graduates": {
      "total": 168,
      "workingCount": 73
    },
    "earnings": {
      "annual": 66199,
      "monthly": 5517,
      "byDemographic": {
        "male": 72403,
        "nonMale": 62459,
        "pellRecipient": 64101,
        "nonPellRecipient": 68398
      }
    },
    "deliveryMethod": 3
  },
  {
    "cipCode": "3017",
    "programName": "Behavioral Sciences.",
    "credentialLevel": "Bachelor's Degree",
    "credentialCode": "3",
    "graduates": {
      "total": 1,
      "workingCount": 0
    },
    "earnings": {
      "annual": 0,
      "monthly": 0,
      "byDemographic": {
        "male": 0,
        "nonMale": 0,
        "pellRecipient": 0,
        "nonPellRecipient": 0
      }
    },
    "deliveryMethod": 3
  },
  {
    "cipCode": "3105",
    "programName": "Health and Physical Education/Fitness.",
    "credentialLevel": "Undergraduate Certificate or Diploma",
    "credentialCode": "1",
    "graduates": {
      "total": 5,
      "workingCount": 0
    },
    "earnings": {
      "annual": 0,
      "monthly": 0,
      "byDemographic": {
        "male": 0,
        "nonMale": 0,
        "pellRecipient": 0,
        "nonPellRecipient": 0
      }
    },
    "deliveryMethod": 3
  },
  {
    "cipCode": "4301",
    "programName": "Criminal Justice and Corrections.",
    "credentialLevel": "Associate's Degree",
    "credentialCode": "2",
    "graduates": {
      "total": 178,
      "workingCount": 175
    },
    "earnings": {
      "annual": 62396,
      "monthly": 5200,
      "byDemographic": {
        "male": 71096,
        "nonMale": 44753,
        "pellRecipient": 59195,
        "nonPellRecipient": 79977
      }
    },
    "deliveryMethod": 3
  },
  {
    "cipCode": "4301",
    "programName": "Criminal Justice and Corrections.",
    "credentialLevel": "Bachelor's Degree",
    "credentialCode": "3",
    "graduates": {
      "total": 263,
      "workingCount": 259
    },
    "earnings": {
      "annual": 61453,
      "monthly": 5121,
      "byDemographic": {
        "male": 67631,
        "nonMale": 49840,
        "pellRecipient": 56316,
        "nonPellRecipient": 85356
      }
    },
    "deliveryMethod": 3
  },
  {
    "cipCode": "4301",
    "programName": "Criminal Justice and Corrections.",
    "credentialLevel": "Master's Degree",
    "credentialCode": "5",
    "graduates": {
      "total": 53,
      "workingCount": 64
    },
    "earnings": {
      "annual": 62524,
      "monthly": 5210,
      "byDemographic": {
        "male": 71445,
        "nonMale": 53902,
        "pellRecipient": 54952,
        "nonPellRecipient": 76226
      }
    },
    "deliveryMethod": 3
  },
  {
    "cipCode": "4302",
    "programName": "Fire Protection.",
    "credentialLevel": "Undergraduate Certificate or Diploma",
    "credentialCode": "1",
    "graduates": {
      "total": 24,
      "workingCount": 0
    },
    "earnings": {
      "annual": 0,
      "monthly": 0,
      "byDemographic": {
        "male": 0,
        "nonMale": 0,
        "pellRecipient": 0,
        "nonPellRecipient": 0
      }
    },
    "deliveryMethod": 3
  },
  {
    "cipCode": "4302",
    "programName": "Fire Protection.",
    "credentialLevel": "Associate's Degree",
    "credentialCode": "2",
    "graduates": {
      "total": 486,
      "workingCount": 251
    },
    "earnings": {
      "annual": 80640,
      "monthly": 6720,
      "byDemographic": {
        "male": 80784,
        "nonMale": 0,
        "pellRecipient": 73277,
        "nonPellRecipient": 90261
      }
    },
    "deliveryMethod": 3
  },
  {
    "cipCode": "4302",
    "programName": "Fire Protection.",
    "credentialLevel": "Bachelor's Degree",
    "credentialCode": "3",
    "graduates": {
      "total": 527,
      "workingCount": 214
    },
    "earnings": {
      "annual": 87912,
      "monthly": 7326,
      "byDemographic": {
        "male": 0,
        "nonMale": 0,
        "pellRecipient": 85248,
        "nonPellRecipient": 92919
      }
    },
    "deliveryMethod": 3
  },
  {
    "cipCode": "4303",
    "programName": "Homeland Security.",
    "credentialLevel": "Bachelor's Degree",
    "credentialCode": "3",
    "graduates": {
      "total": 67,
      "workingCount": 0
    },
    "earnings": {
      "annual": 0,
      "monthly": 0,
      "byDemographic": {
        "male": 0,
        "nonMale": 0,
        "pellRecipient": 0,
        "nonPellRecipient": 0
      }
    },
    "deliveryMethod": 3
  },
  {
    "cipCode": "4303",
    "programName": "Homeland Security.",
    "credentialLevel": "Master's Degree",
    "credentialCode": "5",
    "graduates": {
      "total": 175,
      "workingCount": 96
    },
    "earnings": {
      "annual": 83721,
      "monthly": 6977,
      "byDemographic": {
        "male": 85410,
        "nonMale": 74292,
        "pellRecipient": 82722,
        "nonPellRecipient": 83860
      }
    },
    "deliveryMethod": 3
  },
  {
    "cipCode": "4404",
    "programName": "Public Administration.",
    "credentialLevel": "Master's Degree",
    "credentialCode": "5",
    "graduates": {
      "total": 127,
      "workingCount": 29
    },
    "earnings": {
      "annual": 80102,
      "monthly": 6675,
      "byDemographic": {
        "male": 0,
        "nonMale": 0,
        "pellRecipient": 0,
        "nonPellRecipient": 0
      }
    },
    "deliveryMethod": 3
  },
  {
    "cipCode": "4404",
    "programName": "Public Administration.",
    "credentialLevel": "Graduate/Professional Certificate",
    "credentialCode": "8",
    "graduates": {
      "total": 2,
      "workingCount": 0
    },
    "earnings": {
      "annual": 0,
      "monthly": 0,
      "byDemographic": {
        "male": 0,
        "nonMale": 0,
        "pellRecipient": 0,
        "nonPellRecipient": 0
      }
    },
    "deliveryMethod": 3
  },
  {
    "cipCode": "5107",
    "programName": "Health and Medical Administrative Services.",
    "credentialLevel": "Associate's Degree",
    "credentialCode": "2",
    "graduates": {
      "total": 47,
      "workingCount": 0
    },
    "earnings": {
      "annual": 0,
      "monthly": 0,
      "byDemographic": {
        "male": 0,
        "nonMale": 0,
        "pellRecipient": 0,
        "nonPellRecipient": 0
      }
    },
    "deliveryMethod": 3
  },
  {
    "cipCode": "5107",
    "programName": "Health and Medical Administrative Services.",
    "credentialLevel": "Bachelor's Degree",
    "credentialCode": "3",
    "graduates": {
      "total": 192,
      "workingCount": 178
    },
    "earnings": {
      "annual": 60480,
      "monthly": 5040,
      "byDemographic": {
        "male": 79206,
        "nonMale": 55815,
        "pellRecipient": 56150,
        "nonPellRecipient": 0
      }
    },
    "deliveryMethod": 3
  },
  {
    "cipCode": "5107",
    "programName": "Health and Medical Administrative Services.",
    "credentialLevel": "Graduate/Professional Certificate",
    "credentialCode": "8",
    "graduates": {
      "total": 7,
      "workingCount": 0
    },
    "earnings": {
      "annual": 0,
      "monthly": 0,
      "byDemographic": {
        "male": 0,
        "nonMale": 0,
        "pellRecipient": 0,
        "nonPellRecipient": 0
      }
    },
    "deliveryMethod": 3
  },
  {
    "cipCode": "5109",
    "programName": "Allied Health Diagnostic, Intervention, and Treatment Professions.",
    "credentialLevel": "Associate's Degree",
    "credentialCode": "2",
    "graduates": {
      "total": 12,
      "workingCount": 0
    },
    "earnings": {
      "annual": 0,
      "monthly": 0,
      "byDemographic": {
        "male": 0,
        "nonMale": 0,
        "pellRecipient": 0,
        "nonPellRecipient": 0
      }
    },
    "deliveryMethod": 3
  },
  {
    "cipCode": "5109",
    "programName": "Allied Health Diagnostic, Intervention, and Treatment Professions.",
    "credentialLevel": "Bachelor's Degree",
    "credentialCode": "3",
    "graduates": {
      "total": 64,
      "workingCount": 0
    },
    "earnings": {
      "annual": 0,
      "monthly": 0,
      "byDemographic": {
        "male": 0,
        "nonMale": 0,
        "pellRecipient": 0,
        "nonPellRecipient": 0
      }
    },
    "deliveryMethod": 3
  },
  {
    "cipCode": "5115",
    "programName": "Mental and Social Health Services and Allied Professions.",
    "credentialLevel": "Undergraduate Certificate or Diploma",
    "credentialCode": "1",
    "graduates": {
      "total": 4,
      "workingCount": 0
    },
    "earnings": {
      "annual": 0,
      "monthly": 0,
      "byDemographic": {
        "male": 0,
        "nonMale": 0,
        "pellRecipient": 0,
        "nonPellRecipient": 0
      }
    },
    "deliveryMethod": 3
  },
  {
    "cipCode": "5115",
    "programName": "Mental and Social Health Services and Allied Professions.",
    "credentialLevel": "Bachelor's Degree",
    "credentialCode": "3",
    "graduates": {
      "total": 92,
      "workingCount": 42
    },
    "earnings": {
      "annual": 44714,
      "monthly": 3726,
      "byDemographic": {
        "male": 0,
        "nonMale": 0,
        "pellRecipient": 0,
        "nonPellRecipient": 0
      }
    },
    "deliveryMethod": 3
  },
  {
    "cipCode": "5122",
    "programName": "Public Health.",
    "credentialLevel": "Master's Degree",
    "credentialCode": "5",
    "graduates": {
      "total": 93,
      "workingCount": 0
    },
    "earnings": {
      "annual": 0,
      "monthly": 0,
      "byDemographic": {
        "male": 0,
        "nonMale": 0,
        "pellRecipient": 0,
        "nonPellRecipient": 0
      }
    },
    "deliveryMethod": 3
  },
  {
    "cipCode": "5202",
    "programName": "Business Administration, Management and Operations.",
    "credentialLevel": "Undergraduate Certificate or Diploma",
    "credentialCode": "1",
    "graduates": {
      "total": 11,
      "workingCount": 26
    },
    "earnings": {
      "annual": 78497,
      "monthly": 6541,
      "byDemographic": {
        "male": 0,
        "nonMale": 0,
        "pellRecipient": 0,
        "nonPellRecipient": 0
      }
    },
    "deliveryMethod": 3
  },
  {
    "cipCode": "5202",
    "programName": "Business Administration, Management and Operations.",
    "credentialLevel": "Associate's Degree",
    "credentialCode": "2",
    "graduates": {
      "total": 327,
      "workingCount": 336
    },
    "earnings": {
      "annual": 51885,
      "monthly": 4324,
      "byDemographic": {
        "male": 64881,
        "nonMale": 43216,
        "pellRecipient": 47702,
        "nonPellRecipient": 69969
      }
    },
    "deliveryMethod": 3
  },
  {
    "cipCode": "5202",
    "programName": "Business Administration, Management and Operations.",
    "credentialLevel": "Bachelor's Degree",
    "credentialCode": "3",
    "graduates": {
      "total": 823,
      "workingCount": 706
    },
    "earnings": {
      "annual": 63635,
      "monthly": 5303,
      "byDemographic": {
        "male": 74242,
        "nonMale": 56871,
        "pellRecipient": 58927,
        "nonPellRecipient": 85813
      }
    },
    "deliveryMethod": 3
  },
  {
    "cipCode": "5202",
    "programName": "Business Administration, Management and Operations.",
    "credentialLevel": "Master's Degree",
    "credentialCode": "5",
    "graduates": {
      "total": 1241,
      "workingCount": 719
    },
    "earnings": {
      "annual": 75617,
      "monthly": 6301,
      "byDemographic": {
        "male": 89813,
        "nonMale": 69242,
        "pellRecipient": 72663,
        "nonPellRecipient": 83925
      }
    },
    "deliveryMethod": 3
  },
  {
    "cipCode": "5202",
    "programName": "Business Administration, Management and Operations.",
    "credentialLevel": "Doctoral Degree",
    "credentialCode": "6",
    "graduates": {
      "total": 42,
      "workingCount": 0
    },
    "earnings": {
      "annual": 0,
      "monthly": 0,
      "byDemographic": {
        "male": 0,
        "nonMale": 0,
        "pellRecipient": 0,
        "nonPellRecipient": 0
      }
    },
    "deliveryMethod": 3
  },
  {
    "cipCode": "5202",
    "programName": "Business Administration, Management and Operations.",
    "credentialLevel": "Graduate/Professional Certificate",
    "credentialCode": "8",
    "graduates": {
      "total": 6,
      "workingCount": 0
    },
    "earnings": {
      "annual": 0,
      "monthly": 0,
      "byDemographic": {
        "male": 0,
        "nonMale": 0,
        "pellRecipient": 0,
        "nonPellRecipient": 0
      }
    },
    "deliveryMethod": 3
  },
  {
    "cipCode": "5208",
    "programName": "Finance and Financial Management Services.",
    "credentialLevel": "Undergraduate Certificate or Diploma",
    "credentialCode": "1",
    "graduates": {
      "total": 2,
      "workingCount": 0
    },
    "earnings": {
      "annual": 0,
      "monthly": 0,
      "byDemographic": {
        "male": 0,
        "nonMale": 0,
        "pellRecipient": 0,
        "nonPellRecipient": 0
      }
    },
    "deliveryMethod": 3
  },
  {
    "cipCode": "5208",
    "programName": "Finance and Financial Management Services.",
    "credentialLevel": "Graduate/Professional Certificate",
    "credentialCode": "8",
    "graduates": {
      "total": 2,
      "workingCount": 0
    },
    "earnings": {
      "annual": 0,
      "monthly": 0,
      "byDemographic": {
        "male": 0,
        "nonMale": 0,
        "pellRecipient": 0,
        "nonPellRecipient": 0
      }
    },
    "deliveryMethod": 3
  },
  {
    "cipCode": "5209",
    "programName": "Hospitality Administration/Management.",
    "credentialLevel": "Undergraduate Certificate or Diploma",
    "credentialCode": "1",
    "graduates": {
      "total": 1,
      "workingCount": 0
    },
    "earnings": {
      "annual": 0,
      "monthly": 0,
      "byDemographic": {
        "male": 0,
        "nonMale": 0,
        "pellRecipient": 0,
        "nonPellRecipient": 0
      }
    },
    "deliveryMethod": 3
  },
  {
    "cipCode": "5210",
    "programName": "Human Resources Management and Services.",
    "credentialLevel": "Undergraduate Certificate or Diploma",
    "credentialCode": "1",
    "graduates": {
      "total": 20,
      "workingCount": 30
    },
    "earnings": {
      "annual": 57864,
      "monthly": 4822,
      "byDemographic": {
        "male": 0,
        "nonMale": 0,
        "pellRecipient": 0,
        "nonPellRecipient": 0
      }
    },
    "deliveryMethod": 3
  },
  {
    "cipCode": "5210",
    "programName": "Human Resources Management and Services.",
    "credentialLevel": "Bachelor's Degree",
    "credentialCode": "3",
    "graduates": {
      "total": 165,
      "workingCount": 72
    },
    "earnings": {
      "annual": 59483,
      "monthly": 4957,
      "byDemographic": {
        "male": 69086,
        "nonMale": 54450,
        "pellRecipient": 0,
        "nonPellRecipient": 0
      }
    },
    "deliveryMethod": 3
  },
  {
    "cipCode": "5210",
    "programName": "Human Resources Management and Services.",
    "credentialLevel": "Graduate/Professional Certificate",
    "credentialCode": "8",
    "graduates": {
      "total": 15,
      "workingCount": 0
    },
    "earnings": {
      "annual": 0,
      "monthly": 0,
      "byDemographic": {
        "male": 0,
        "nonMale": 0,
        "pellRecipient": 0,
        "nonPellRecipient": 0
      }
    },
    "deliveryMethod": 3
  },
  {
    "cipCode": "5214",
    "programName": "Marketing.",
    "credentialLevel": "Undergraduate Certificate or Diploma",
    "credentialCode": "1",
    "graduates": {
      "total": 1,
      "workingCount": 0
    },
    "earnings": {
      "annual": 0,
      "monthly": 0,
      "byDemographic": {
        "male": 0,
        "nonMale": 0,
        "pellRecipient": 0,
        "nonPellRecipient": 0
      }
    },
    "deliveryMethod": 3
  },
  {
    "cipCode": "5214",
    "programName": "Marketing.",
    "credentialLevel": "Graduate/Professional Certificate",
    "credentialCode": "8",
    "graduates": {
      "total": 2,
      "workingCount": 0
    },
    "earnings": {
      "annual": 0,
      "monthly": 0,
      "byDemographic": {
        "male": 0,
        "nonMale": 0,
        "pellRecipient": 0,
        "nonPellRecipient": 0
      }
    },
    "deliveryMethod": 3
  }
]