[
  {
    "cipCode": "1108",
    "programName": "Computer Software and Media Applications.",
    "credentialLevel": "Undergraduate Certificate or Diploma",
    "credentialCode": "1",
    "graduates": {
      "total": 13,
      "workingCount": 0
    },
    "earnings": {
      "annual": 0,
      "monthly": 0,
      "byDemographic": {
        "male": 0,
        "nonMale": 0,
        "pellRecipient": 0,
        "nonPellRecipient": 0
      }
    },
    "deliveryMethod": 1
  },
  {
    "cipCode": "1205",
    "programName": "Culinary Arts and Related Services.",
    "credentialLevel": "Undergraduate Certificate or Diploma",
    "credentialCode": "1",
    "graduates": {
      "total": 47,
      "workingCount": 59
    },
    "earnings": {
      "annual": 10132,
      "monthly": 844,
      "byDemographic": {
        "male": 9578,
        "nonMale": 10495,
        "pellRecipient": 0,
        "nonPellRecipient": 0
      }
    },
    "deliveryMethod": 1
  },
  {
    "cipCode": "1907",
    "programName": "Human Development, Family Studies, and Related Services.",
    "credentialLevel": "Undergraduate Certificate or Diploma",
    "credentialCode": "1",
    "graduates": {
      "total": 8,
      "workingCount": 0
    },
    "earnings": {
      "annual": 0,
      "monthly": 0,
      "byDemographic": {
        "male": 0,
        "nonMale": 0,
        "pellRecipient": 0,
        "nonPellRecipient": 0
      }
    },
    "deliveryMethod": 1
  },
  {
    "cipCode": "4303",
    "programName": "Homeland Security.",
    "credentialLevel": "Undergraduate Certificate or Diploma",
    "credentialCode": "1",
    "graduates": {
      "total": 15,
      "workingCount": 0
    },
    "earnings": {
      "annual": 0,
      "monthly": 0,
      "byDemographic": {
        "male": 0,
        "nonMale": 0,
        "pellRecipient": 0,
        "nonPellRecipient": 0
      }
    },
    "deliveryMethod": 1
  },
  {
    "cipCode": "4303",
    "programName": "Homeland Security.",
    "credentialLevel": "Associate's Degree",
    "credentialCode": "2",
    "graduates": {
      "total": 10,
      "workingCount": 0
    },
    "earnings": {
      "annual": 0,
      "monthly": 0,
      "byDemographic": {
        "male": 0,
        "nonMale": 0,
        "pellRecipient": 0,
        "nonPellRecipient": 0
      }
    },
    "deliveryMethod": 1
  },
  {
    "cipCode": "4701",
    "programName": "Electrical/Electronics Maintenance and Repair Technology.",
    "credentialLevel": "Associate's Degree",
    "credentialCode": "2",
    "graduates": {
      "total": 11,
      "workingCount": 0
    },
    "earnings": {
      "annual": 0,
      "monthly": 0,
      "byDemographic": {
        "male": 0,
        "nonMale": 0,
        "pellRecipient": 0,
        "nonPellRecipient": 0
      }
    },
    "deliveryMethod": 1
  },
  {
    "cipCode": "5106",
    "programName": "Dental Support Services and Allied Professions.",
    "credentialLevel": "Undergraduate Certificate or Diploma",
    "credentialCode": "1",
    "graduates": {
      "total": 0,
      "workingCount": 22
    },
    "earnings": {
      "annual": 20512,
      "monthly": 1709,
      "byDemographic": {
        "male": 0,
        "nonMale": 0,
        "pellRecipient": 0,
        "nonPellRecipient": 0
      }
    },
    "deliveryMethod": 1
  },
  {
    "cipCode": "5107",
    "programName": "Health and Medical Administrative Services.",
    "credentialLevel": "Undergraduate Certificate or Diploma",
    "credentialCode": "1",
    "graduates": {
      "total": 23,
      "workingCount": 22
    },
    "earnings": {
      "annual": 16327,
      "monthly": 1361,
      "byDemographic": {
        "male": 0,
        "nonMale": 0,
        "pellRecipient": 0,
        "nonPellRecipient": 0
      }
    },
    "deliveryMethod": 1
  },
  {
    "cipCode": "5107",
    "programName": "Health and Medical Administrative Services.",
    "credentialLevel": "Associate's Degree",
    "credentialCode": "2",
    "graduates": {
      "total": 0,
      "workingCount": 21
    },
    "earnings": {
      "annual": 16836,
      "monthly": 1403,
      "byDemographic": {
        "male": 0,
        "nonMale": 0,
        "pellRecipient": 0,
        "nonPellRecipient": 0
      }
    },
    "deliveryMethod": 1
  },
  {
    "cipCode": "5108",
    "programName": "Allied Health and Medical Assisting Services.",
    "credentialLevel": "Undergraduate Certificate or Diploma",
    "credentialCode": "1",
    "graduates": {
      "total": 5,
      "workingCount": 0
    },
    "earnings": {
      "annual": 0,
      "monthly": 0,
      "byDemographic": {
        "male": 0,
        "nonMale": 0,
        "pellRecipient": 0,
        "nonPellRecipient": 0
      }
    },
    "deliveryMethod": 1
  },
  {
    "cipCode": "5109",
    "programName": "Allied Health Diagnostic, Intervention, and Treatment Professions.",
    "credentialLevel": "Associate's Degree",
    "credentialCode": "2",
    "graduates": {
      "total": 13,
      "workingCount": 0
    },
    "earnings": {
      "annual": 0,
      "monthly": 0,
      "byDemographic": {
        "male": 0,
        "nonMale": 0,
        "pellRecipient": 0,
        "nonPellRecipient": 0
      }
    },
    "deliveryMethod": 1
  },
  {
    "cipCode": "5126",
    "programName": "Health Aides/Attendants/Orderlies.",
    "credentialLevel": "Undergraduate Certificate or Diploma",
    "credentialCode": "1",
    "graduates": {
      "total": 11,
      "workingCount": 0
    },
    "earnings": {
      "annual": 0,
      "monthly": 0,
      "byDemographic": {
        "male": 0,
        "nonMale": 0,
        "pellRecipient": 0,
        "nonPellRecipient": 0
      }
    },
    "deliveryMethod": 1
  },
  {
    "cipCode": "5135",
    "programName": "Somatic Bodywork and Related Therapeutic Services.",
    "credentialLevel": "Undergraduate Certificate or Diploma",
    "credentialCode": "1",
    "graduates": {
      "total": 7,
      "workingCount": 0
    },
    "earnings": {
      "annual": 0,
      "monthly": 0,
      "byDemographic": {
        "male": 0,
        "nonMale": 0,
        "pellRecipient": 0,
        "nonPellRecipient": 0
      }
    },
    "deliveryMethod": 1
  },
  {
    "cipCode": "5138",
    "programName": "Registered Nursing, Nursing Administration, Nursing Research and Clinical Nursing.",
    "credentialLevel": "Associate's Degree",
    "credentialCode": "2",
    "graduates": {
      "total": 3,
      "workingCount": 0
    },
    "earnings": {
      "annual": 0,
      "monthly": 0,
      "byDemographic": {
        "male": 0,
        "nonMale": 0,
        "pellRecipient": 0,
        "nonPellRecipient": 0
      }
    },
    "deliveryMethod": 1
  },
  {
    "cipCode": "5214",
    "programName": "Marketing.",
    "credentialLevel": "Associate's Degree",
    "credentialCode": "2",
    "graduates": {
      "total": 7,
      "workingCount": 0
    },
    "earnings": {
      "annual": 0,
      "monthly": 0,
      "byDemographic": {
        "male": 0,
        "nonMale": 0,
        "pellRecipient": 0,
        "nonPellRecipient": 0
      }
    },
    "deliveryMethod": 1
  },
  {
    "cipCode": "5219",
    "programName": "Specialized Sales, Merchandising and  Marketing Operations.",
    "credentialLevel": "Undergraduate Certificate or Diploma",
    "credentialCode": "1",
    "graduates": {
      "total": 1,
      "workingCount": 0
    },
    "earnings": {
      "annual": 0,
      "monthly": 0,
      "byDemographic": {
        "male": 0,
        "nonMale": 0,
        "pellRecipient": 0,
        "nonPellRecipient": 0
      }
    },
    "deliveryMethod": 1
  }
]