[
  {
    "cipCode": "1104",
    "programName": "Information Science/Studies.",
    "credentialLevel": "Bachelor's Degree",
    "credentialCode": "3",
    "graduates": {
      "total": 19,
      "workingCount": 136
    },
    "earnings": {
      "annual": 71313,
      "monthly": 5943,
      "byDemographic": {
        "male": 74777,
        "nonMale": 62417,
        "pellRecipient": 66350,
        "nonPellRecipient": 88715
      }
    },
    "deliveryMethod": 3
  },
  {
    "cipCode": "2313",
    "programName": "Rhetoric and Composition/Writing Studies.",
    "credentialLevel": "Undergraduate Certificate or Diploma",
    "credentialCode": "1",
    "graduates": {
      "total": 1,
      "workingCount": 0
    },
    "earnings": {
      "annual": 0,
      "monthly": 0,
      "byDemographic": {
        "male": 0,
        "nonMale": 0,
        "pellRecipient": 0,
        "nonPellRecipient": 0
      }
    },
    "deliveryMethod": 3
  },
  {
    "cipCode": "2401",
    "programName": "Liberal Arts and Sciences, General Studies and Humanities.",
    "credentialLevel": "Associate's Degree",
    "credentialCode": "2",
    "graduates": {
      "total": 26,
      "workingCount": 189
    },
    "earnings": {
      "annual": 47037,
      "monthly": 3920,
      "byDemographic": {
        "male": 51811,
        "nonMale": 43935,
        "pellRecipient": 47953,
        "nonPellRecipient": 46377
      }
    },
    "deliveryMethod": 3
  },
  {
    "cipCode": "5100",
    "programName": "Health Services/Allied Health/Health Sciences, General.",
    "credentialLevel": "Bachelor's Degree",
    "credentialCode": "3",
    "graduates": {
      "total": 9,
      "workingCount": 0
    },
    "earnings": {
      "annual": 0,
      "monthly": 0,
      "byDemographic": {
        "male": 0,
        "nonMale": 0,
        "pellRecipient": 0,
        "nonPellRecipient": 0
      }
    },
    "deliveryMethod": 3
  },
  {
    "cipCode": "5110",
    "programName": "Clinical/Medical Laboratory Science/Research and Allied Professions.",
    "credentialLevel": "Bachelor's Degree",
    "credentialCode": "3",
    "graduates": {
      "total": 13,
      "workingCount": 29
    },
    "earnings": {
      "annual": 68982,
      "monthly": 5749,
      "byDemographic": {
        "male": 0,
        "nonMale": 0,
        "pellRecipient": 0,
        "nonPellRecipient": 0
      }
    },
    "deliveryMethod": 3
  },
  {
    "cipCode": "5138",
    "programName": "Registered Nursing, Nursing Administration, Nursing Research and Clinical Nursing.",
    "credentialLevel": "Bachelor's Degree",
    "credentialCode": "3",
    "graduates": {
      "total": 57,
      "workingCount": 227
    },
    "earnings": {
      "annual": 77482,
      "monthly": 6457,
      "byDemographic": {
        "male": 85752,
        "nonMale": 75767,
        "pellRecipient": 75135,
        "nonPellRecipient": 80986
      }
    },
    "deliveryMethod": 3
  }
]